tcs_engine/__init__.py
tcs_engine/cli.py
tcs_engine/core/__init__.py
tcs_engine/core/agent.py
tcs_engine/core/commitment_ledger.py
tcs_engine/core/existential_load.py
tcs_engine/core/lockin_engine.py
tcs_engine/core/regret_accumulator.py
tcs_engine/core/self_prediction_loss.py
tcs_engine/core/sii.py
tcs_engine/core/temporal_drift.py
tcs_engine/pro_modules/__init__.py
tcs_engine/pro_modules/alignment_audit.py
tcs_engine/pro_modules/dashboard_api.py
tcs_engine/pro_modules/experiment_manager.py
tcs_engine/pro_modules/license.py
tcs_engine/pro_modules/phase_transition_scan.py
tcs_engine/pro_modules/realtime_visualizer.py
tcs_engine/utils/__init__.py
tcs_engine/utils/runtime_checks.py
tcs_engine-0.1.0.dist-info/licenses/LICENSE-CORE.txt
tcs_engine-0.1.0.dist-info/licenses/LICENSE-PRO.txt
tcs_engine-0.1.0.dist-info/METADATA
tcs_engine-0.1.0.dist-info/WHEEL
tcs_engine-0.1.0.dist-info/entry_points.txt
tcs_engine-0.1.0.dist-info/top_level.txt
tcs_engine-0.1.0.dist-info/RECORD
