Metadata-Version: 2.4
Name: tcs_engine
Version: 0.1.0
Summary: Temporal Constraint Engine for multi-agent temporal selfhood analysis.
Author-email: Nicolai Mahangi <nickmahangi@gmail.com>
License: MIT
Project-URL: Homepage, https://github.com/nickmahangi/tcs-engine
Project-URL: Repository, https://github.com/nickmahangi/tcs-engine
Project-URL: Documentation, https://github.com/nickmahangi/tcs-engine#readme
Keywords: ai,multi-agent,temporal-constraints,ai-safety,cognitive-architecture
Classifier: Development Status :: 4 - Beta
Classifier: Intended Audience :: Science/Research
Classifier: License :: OSI Approved :: MIT License
Classifier: Programming Language :: Python :: 3
Classifier: Programming Language :: Python :: 3.9
Classifier: Programming Language :: Python :: 3.10
Classifier: Programming Language :: Python :: 3.11
Classifier: Programming Language :: Python :: 3.12
Classifier: Topic :: Scientific/Engineering :: Artificial Intelligence
Requires-Python: >=3.9
License-File: LICENSE-CORE.txt
License-File: LICENSE-PRO.txt
Requires-Dist: numpy>=1.24
Requires-Dist: scipy>=1.10
Requires-Dist: click>=8.1
Requires-Dist: rich>=13.0
Dynamic: license-file
